tensor_drpi/__init__.py
tensor_drpi/tensor_drpi.py
tensordrpi-0.0.1.dist-info/METADATA
tensordrpi-0.0.1.dist-info/WHEEL
tensordrpi-0.0.1.dist-info/top_level.txt
tensordrpi-0.0.1.dist-info/RECORD
