Metadata-Version: 2.1
Name: tensordrpi
Version: 0.0.1
Summary: A basic Machine Learning package
Author: Florian Scadav
